{"version":"0.0.0","commands":{"create":{"id":"create","description":"Describe the command here\n...\nExtra documentation goes here\n","pluginName":"semaver","pluginType":"core","aliases":[],"flags":{"initial":{"name":"initial","type":"option","char":"i","description":"initial version","required":false}},"args":[]},"update":{"id":"update","description":"Describe the command here\n...\nExtra documentation goes here\n","pluginName":"semaver","pluginType":"core","aliases":[],"flags":{"major":{"name":"major","type":"boolean","char":"x","description":"increase major version","required":false,"allowNo":false},"minor":{"name":"minor","type":"boolean","char":"y","description":"increase minor version","required":false,"allowNo":false},"patch":{"name":"patch","type":"boolean","char":"z","description":"increase patch version","required":false,"allowNo":false},"tag":{"name":"tag","type":"boolean","char":"t","description":"tag version in git","required":false,"allowNo":false}},"args":[]}}}